sphinx_inventory_builder/__init__.py
sphinx_inventory_builder-0.1.0.dist-info/LICENSE
sphinx_inventory_builder-0.1.0.dist-info/METADATA
sphinx_inventory_builder-0.1.0.dist-info/WHEEL
sphinx_inventory_builder-0.1.0.dist-info/top_level.txt
sphinx_inventory_builder-0.1.0.dist-info/RECORD
